{
    "multiplier":{
        "100":"\u137b",
        "1000":"\u137c"

    },
    "numbers": {
        "0": "-",
        "1": "\u1369",
        "no": "\u136a",
        "2": "\u136a",
        "3": "\u136b",
        "4": "\u136c",
        "5": "\u136d",
        "6": "\u136e",
        "7": "\u136f",
        "8": "\u1370",
        "9": "\u1371",
        "10": "\u1372",
        "11": "\u1372\u1369",
        "12": "\u1372\u136a",
        "13": "\u1372\u136b",
        "14": "\u1372\u136c",
        "15": "\u1372\u136d",
        "16": "\u1372\u136e",
        "17": "\u1372\u136f",
        "18": "\u1372\u1370",
        "19": "\u1372\u1371",
        "20": "\u1373",
        "21": "\u1373\u1369",
        "22": "\u1373\u136a",
        "23": "\u1373\u136b",
        "24": "\u1373\u136c",
        "25": "\u1373\u136d",
        "26": "\u1373\u136e",
        "27": "\u1373\u136f",
        "28": "\u1373\u1370",
        "29": "\u1373\u1371",
        "30": "\u1374",
        "31": "\u1374\u1369",
        "32": "\u1374\u136a",
        "33": "\u1374\u136b",
        "34": "\u1374\u136c",
        "35": "\u1374\u136d",
        "36": "\u1374\u136e",
        "37": "\u1374\u136f",
        "38": "\u1374\u1370",
        "39": "\u1374\u1371",
        "40": "\u1375",
        "41": "\u1375\u1369",
        "42": "\u1375\u136a",
        "43": "\u1375\u136b",
        "44": "\u1375\u136c",
        "45": "\u1375\u136d",
        "46": "\u1375\u136e",
        "47": "\u1375\u136f",
        "48": "\u1375\u1370",
        "49": "\u1375\u1371",
        "50": "\u1376",
        "51": "\u1376\u1369",
        "52": "\u1376\u136a",
        "53": "\u1376\u136b",
        "54": "\u1376\u136c",
        "55": "\u1376\u136d",
        "56": "\u1376\u136e",
        "57": "\u1376\u136f",
        "58": "\u1376\u1370",
        "59": "\u1376\u1371",
        "60": "\u1377",
        "61": "\u1377\u1369",
        "62": "\u1377\u136a",
        "63": "\u1377\u136b",
        "64": "\u1377\u136c",
        "65": "\u1377\u136d",
        "66": "\u1377\u136e",
        "67": "\u1377\u136f",
        "68": "\u1377\u1370",
        "69": "\u1377\u1371",
        "70": "\u1378",
        "71": "\u1378\u1369",
        "72": "\u1378\u136a",
        "73": "\u1378\u136b",
        "74": "\u1378\u136c",
        "75": "\u1378\u136d",
        "76": "\u1378\u136e",
        "77": "\u1378\u136f",
        "78": "\u1378\u1370",
        "79": "\u1378\u1371",
        "80": "\u1379",
        "81": "\u1379\u1369",
        "82": "\u1379\u136a",
        "83": "\u1379\u136b",
        "84": "\u1379\u136c",
        "85": "\u1379\u136d",
        "86": "\u1379\u136e",
        "87": "\u1379\u136f",
        "88": "\u1379\u1370",
        "89": "\u1379\u1371",
        "90": "\u137a",
        "91": "\u137a\u1369",
        "92": "\u137a\u136a",
        "93": "\u137a\u136b",
        "94": "\u137a\u136c",
        "95": "\u137a\u136d",
        "96": "\u137a\u136e",
        "97": "\u137a\u136f",
        "98": "\u137a\u1370",
        "99": "\u137a\u1371",
        "100": "\u137b",
        "101": "\u137b\u1369",
        "102": "\u137b\u136a",
        "103": "\u137b\u136b",
        "104": "\u137b\u136c",
        "105": "\u137b\u136d",
        "106": "\u137b\u136e",
        "107": "\u137b\u136f",
        "108": "\u137b\u1370",
        "109": "\u137b\u1371",
        "110": "\u137b\u1372",
        "111": "\u137b\u1372\u1369",
        "112": "\u137b\u1372\u136a",
        "113": "\u137b\u1372\u136b",
        "114": "\u137b\u1372\u136c",
        "115": "\u137b\u1372\u136d",
        "116": "\u137b\u1372\u136e",
        "117": "\u137b\u1372\u136f",
        "118": "\u137b\u1372\u1370",
        "119": "\u137b\u1372\u1371",
        "120": "\u137b\u1373",
        "121": "\u137b\u1373\u1369",
        "122": "\u137b\u1373\u136a",
        "123": "\u137b\u1373\u136b",
        "124": "\u137b\u1373\u136c",
        "125": "\u137b\u1373\u136d",
        "126": "\u137b\u1373\u136e",
        "127": "\u137b\u1373\u136f",
        "128": "\u137b\u1373\u1370",
        "129": "\u137b\u1373\u1371",
        "130": "\u137b\u1374",
        "131": "\u137b\u1374\u1369",
        "132": "\u137b\u1374\u136a",
        "133": "\u137b\u1374\u136b",
        "134": "\u137b\u1374\u136c",
        "135": "\u137b\u1374\u136d",
        "136": "\u137b\u1374\u136e",
        "137": "\u137b\u1374\u136f",
        "138": "\u137b\u1374\u1370",
        "139": "\u137b\u1374\u1371",
        "140": "\u137b\u1375",
        "141": "\u137b\u1375\u1369",
        "142": "\u137b\u1375\u136a",
        "143": "\u137b\u1375\u136b",
        "144": "\u137b\u1375\u136c",
        "145": "\u137b\u1375\u136d",
        "146": "\u137b\u1375\u136e",
        "147": "\u137b\u1375\u136f",
        "148": "\u137b\u1375\u1370",
        "149": "\u137b\u1375\u1371",
        "150": "\u137b\u1376",
        "151": "\u137b\u1376\u1369",
        "152": "\u137b\u1376\u136a",
        "153": "\u137b\u1376\u136b",
        "154": "\u137b\u1376\u136c",
        "155": "\u137b\u1376\u136d",
        "156": "\u137b\u1376\u136e",
        "157": "\u137b\u1376\u136f",
        "158": "\u137b\u1376\u1370",
        "159": "\u137b\u1376\u1371",
        "160": "\u137b\u1377",
        "161": "\u137b\u1377\u1369",
        "162": "\u137b\u1377\u136a",
        "163": "\u137b\u1377\u136b",
        "164": "\u137b\u1377\u136c",
        "165": "\u137b\u1377\u136d",
        "166": "\u137b\u1377\u136e",
        "167": "\u137b\u1377\u136f",
        "168": "\u137b\u1377\u1370",
        "169": "\u137b\u1377\u1371",
        "170": "\u137b\u1378",
        "171": "\u137b\u1378\u1369",
        "172": "\u137b\u1378\u136a",
        "173": "\u137b\u1378\u136b",
        "174": "\u137b\u1378\u136c",
        "175": "\u137b\u1378\u136d",
        "176": "\u137b\u1378\u136e",
        "177": "\u137b\u1378\u136f",
        "178": "\u137b\u1378\u1370",
        "179": "\u137b\u1378\u1371",
        "180": "\u137b\u1379",
        "181": "\u137b\u1379\u1369",
        "182": "\u137b\u1379\u136a",
        "183": "\u137b\u1379\u136b",
        "184": "\u137b\u1379\u136c",
        "185": "\u137b\u1379\u136d",
        "186": "\u137b\u1379\u136e",
        "187": "\u137b\u1379\u136f",
        "188": "\u137b\u1379\u1370",
        "189": "\u137b\u1379\u1371",
        "190": "\u137b\u137a",
        "191": "\u137b\u137a\u1369",
        "192": "\u137b\u137a\u136a",
        "193": "\u137b\u137a\u136b",
        "194": "\u137b\u137a\u136c",
        "195": "\u137b\u137a\u136d",
        "196": "\u137b\u137a\u136e",
        "197": "\u137b\u137a\u136f",
        "198": "\u137b\u137a\u1370",
        "199": "\u137b\u137a\u1371",
        "200": "\u136a\u137b",
        "201": "\u136a\u137b\u1369",
        "202": "\u136a\u137b\u136a",
        "203": "\u136a\u137b\u136b",
        "204": "\u136a\u137b\u136c",
        "205": "\u136a\u137b\u136d",
        "206": "\u136a\u137b\u136e",
        "207": "\u136a\u137b\u136f",
        "208": "\u136a\u137b\u1370",
        "209": "\u136a\u137b\u1371",
        "210": "\u136a\u137b\u1372",
        "211": "\u136a\u137b\u1372\u1369",
        "212": "\u136a\u137b\u1372\u136a",
        "213": "\u136a\u137b\u1372\u136b",
        "214": "\u136a\u137b\u1372\u136c",
        "215": "\u136a\u137b\u1372\u136d",
        "216": "\u136a\u137b\u1372\u136e",
        "217": "\u136a\u137b\u1372\u136f",
        "218": "\u136a\u137b\u1372\u1370",
        "219": "\u136a\u137b\u1372\u1371",
        "220": "\u136a\u137b\u1373",
        "221": "\u136a\u137b\u1373\u1369",
        "222": "\u136a\u137b\u1373\u136a",
        "223": "\u136a\u137b\u1373\u136b",
        "224": "\u136a\u137b\u1373\u136c",
        "225": "\u136a\u137b\u1373\u136d",
        "226": "\u136a\u137b\u1373\u136e",
        "227": "\u136a\u137b\u1373\u136f",
        "228": "\u136a\u137b\u1373\u1370",
        "229": "\u136a\u137b\u1373\u1371",
        "230": "\u136a\u137b\u1374",
        "231": "\u136a\u137b\u1374\u1369",
        "232": "\u136a\u137b\u1374\u136a",
        "233": "\u136a\u137b\u1374\u136b",
        "234": "\u136a\u137b\u1374\u136c",
        "235": "\u136a\u137b\u1374\u136d",
        "236": "\u136a\u137b\u1374\u136e",
        "237": "\u136a\u137b\u1374\u136f",
        "238": "\u136a\u137b\u1374\u1370",
        "239": "\u136a\u137b\u1374\u1371",
        "240": "\u136a\u137b\u1375",
        "241": "\u136a\u137b\u1375\u1369",
        "242": "\u136a\u137b\u1375\u136a",
        "243": "\u136a\u137b\u1375\u136b",
        "244": "\u136a\u137b\u1375\u136c",
        "245": "\u136a\u137b\u1375\u136d",
        "246": "\u136a\u137b\u1375\u136e",
        "247": "\u136a\u137b\u1375\u136f",
        "248": "\u136a\u137b\u1375\u1370",
        "249": "\u136a\u137b\u1375\u1371",
        "250": "\u136a\u137b\u1376",
        "251": "\u136a\u137b\u1376\u1369",
        "252": "\u136a\u137b\u1376\u136a",
        "253": "\u136a\u137b\u1376\u136b",
        "254": "\u136a\u137b\u1376\u136c",
        "255": "\u136a\u137b\u1376\u136d",
        "256": "\u136a\u137b\u1376\u136e",
        "257": "\u136a\u137b\u1376\u136f",
        "258": "\u136a\u137b\u1376\u1370",
        "259": "\u136a\u137b\u1376\u1371",
        "260": "\u136a\u137b\u1377",
        "261": "\u136a\u137b\u1377\u1369",
        "262": "\u136a\u137b\u1377\u136a",
        "263": "\u136a\u137b\u1377\u136b",
        "264": "\u136a\u137b\u1377\u136c",
        "265": "\u136a\u137b\u1377\u136d",
        "266": "\u136a\u137b\u1377\u136e",
        "267": "\u136a\u137b\u1377\u136f",
        "268": "\u136a\u137b\u1377\u1370",
        "269": "\u136a\u137b\u1377\u1371",
        "270": "\u136a\u137b\u1378",
        "271": "\u136a\u137b\u1378\u1369",
        "272": "\u136a\u137b\u1378\u136a",
        "273": "\u136a\u137b\u1378\u136b",
        "274": "\u136a\u137b\u1378\u136c",
        "275": "\u136a\u137b\u1378\u136d",
        "276": "\u136a\u137b\u1378\u136e",
        "277": "\u136a\u137b\u1378\u136f",
        "278": "\u136a\u137b\u1378\u1370",
        "279": "\u136a\u137b\u1378\u1371",
        "280": "\u136a\u137b\u1379",
        "281": "\u136a\u137b\u1379\u1369",
        "282": "\u136a\u137b\u1379\u136a",
        "283": "\u136a\u137b\u1379\u136b",
        "284": "\u136a\u137b\u1379\u136c",
        "285": "\u136a\u137b\u1379\u136d",
        "286": "\u136a\u137b\u1379\u136e",
        "287": "\u136a\u137b\u1379\u136f",
        "288": "\u136a\u137b\u1379\u1370",
        "289": "\u136a\u137b\u1379\u1371",
        "290": "\u136a\u137b\u137a",
        "291": "\u136a\u137b\u137a\u1369",
        "292": "\u136a\u137b\u137a\u136a",
        "293": "\u136a\u137b\u137a\u136b",
        "294": "\u136a\u137b\u137a\u136c",
        "295": "\u136a\u137b\u137a\u136d",
        "296": "\u136a\u137b\u137a\u136e",
        "297": "\u136a\u137b\u137a\u136f",
        "298": "\u136a\u137b\u137a\u1370",
        "299": "\u136a\u137b\u137a\u1371",
        "300": "\u136b\u137b",
        "301": "\u136b\u137b\u1369",
        "302": "\u136b\u137b\u136a",
        "303": "\u136b\u137b\u136b",
        "304": "\u136b\u137b\u136c",
        "305": "\u136b\u137b\u136d",
        "306": "\u136b\u137b\u136e",
        "307": "\u136b\u137b\u136f",
        "308": "\u136b\u137b\u1370",
        "309": "\u136b\u137b\u1371",
        "310": "\u136b\u137b\u1372",
        "311": "\u136b\u137b\u1372\u1369",
        "312": "\u136b\u137b\u1372\u136a",
        "313": "\u136b\u137b\u1372\u136b",
        "314": "\u136b\u137b\u1372\u136c",
        "315": "\u136b\u137b\u1372\u136d",
        "316": "\u136b\u137b\u1372\u136e",
        "317": "\u136b\u137b\u1372\u136f",
        "318": "\u136b\u137b\u1372\u1370",
        "319": "\u136b\u137b\u1372\u1371",
        "320": "\u136b\u137b\u1373",
        "321": "\u136b\u137b\u1373\u1369",
        "322": "\u136b\u137b\u1373\u136a",
        "323": "\u136b\u137b\u1373\u136b",
        "324": "\u136b\u137b\u1373\u136c",
        "325": "\u136b\u137b\u1373\u136d",
        "326": "\u136b\u137b\u1373\u136e",
        "327": "\u136b\u137b\u1373\u136f",
        "328": "\u136b\u137b\u1373\u1370",
        "329": "\u136b\u137b\u1373\u1371",
        "330": "\u136b\u137b\u1374",
        "331": "\u136b\u137b\u1374\u1369",
        "332": "\u136b\u137b\u1374\u136a",
        "333": "\u136b\u137b\u1374\u136b",
        "334": "\u136b\u137b\u1374\u136c",
        "335": "\u136b\u137b\u1374\u136d",
        "336": "\u136b\u137b\u1374\u136e",
        "337": "\u136b\u137b\u1374\u136f",
        "338": "\u136b\u137b\u1374\u1370",
        "339": "\u136b\u137b\u1374\u1371",
        "340": "\u136b\u137b\u1375",
        "341": "\u136b\u137b\u1375\u1369",
        "342": "\u136b\u137b\u1375\u136a",
        "343": "\u136b\u137b\u1375\u136b",
        "344": "\u136b\u137b\u1375\u136c",
        "345": "\u136b\u137b\u1375\u136d",
        "346": "\u136b\u137b\u1375\u136e",
        "347": "\u136b\u137b\u1375\u136f",
        "348": "\u136b\u137b\u1375\u1370",
        "349": "\u136b\u137b\u1375\u1371",
        "350": "\u136b\u137b\u1376",
        "351": "\u136b\u137b\u1376\u1369",
        "352": "\u136b\u137b\u1376\u136a",
        "353": "\u136b\u137b\u1376\u136b",
        "354": "\u136b\u137b\u1376\u136c",
        "355": "\u136b\u137b\u1376\u136d",
        "356": "\u136b\u137b\u1376\u136e",
        "357": "\u136b\u137b\u1376\u136f",
        "358": "\u136b\u137b\u1376\u1370",
        "359": "\u136b\u137b\u1376\u1371",
        "360": "\u136b\u137b\u1377",
        "361": "\u136b\u137b\u1377\u1369",
        "362": "\u136b\u137b\u1377\u136a",
        "363": "\u136b\u137b\u1377\u136b",
        "364": "\u136b\u137b\u1377\u136c",
        "365": "\u136b\u137b\u1377\u136d",
        "366": "\u136b\u137b\u1377\u136e",
        "367": "\u136b\u137b\u1377\u136f",
        "368": "\u136b\u137b\u1377\u1370",
        "369": "\u136b\u137b\u1377\u1371",
        "370": "\u136b\u137b\u1378",
        "371": "\u136b\u137b\u1378\u1369",
        "372": "\u136b\u137b\u1378\u136a",
        "373": "\u136b\u137b\u1378\u136b",
        "374": "\u136b\u137b\u1378\u136c",
        "375": "\u136b\u137b\u1378\u136d",
        "376": "\u136b\u137b\u1378\u136e",
        "377": "\u136b\u137b\u1378\u136f",
        "378": "\u136b\u137b\u1378\u1370",
        "379": "\u136b\u137b\u1378\u1371",
        "380": "\u136b\u137b\u1379",
        "381": "\u136b\u137b\u1379\u1369",
        "382": "\u136b\u137b\u1379\u136a",
        "383": "\u136b\u137b\u1379\u136b",
        "384": "\u136b\u137b\u1379\u136c",
        "385": "\u136b\u137b\u1379\u136d",
        "386": "\u136b\u137b\u1379\u136e",
        "387": "\u136b\u137b\u1379\u136f",
        "388": "\u136b\u137b\u1379\u1370",
        "389": "\u136b\u137b\u1379\u1371",
        "390": "\u136b\u137b\u137a",
        "391": "\u136b\u137b\u137a\u1369",
        "392": "\u136b\u137b\u137a\u136a",
        "393": "\u136b\u137b\u137a\u136b",
        "394": "\u136b\u137b\u137a\u136c",
        "395": "\u136b\u137b\u137a\u136d",
        "396": "\u136b\u137b\u137a\u136e",
        "397": "\u136b\u137b\u137a\u136f",
        "398": "\u136b\u137b\u137a\u1370",
        "399": "\u136b\u137b\u137a\u1371",
        "400": "\u136c\u137b",
        "401": "\u136c\u137b\u1369",
        "402": "\u136c\u137b\u136a",
        "403": "\u136c\u137b\u136b",
        "404": "\u136c\u137b\u136c",
        "405": "\u136c\u137b\u136d",
        "406": "\u136c\u137b\u136e",
        "407": "\u136c\u137b\u136f",
        "408": "\u136c\u137b\u1370",
        "409": "\u136c\u137b\u1371",
        "410": "\u136c\u137b\u1372",
        "411": "\u136c\u137b\u1372\u1369",
        "412": "\u136c\u137b\u1372\u136a",
        "413": "\u136c\u137b\u1372\u136b",
        "414": "\u136c\u137b\u1372\u136c",
        "415": "\u136c\u137b\u1372\u136d",
        "416": "\u136c\u137b\u1372\u136e",
        "417": "\u136c\u137b\u1372\u136f",
        "418": "\u136c\u137b\u1372\u1370",
        "419": "\u136c\u137b\u1372\u1371",
        "420": "\u136c\u137b\u1373",
        "421": "\u136c\u137b\u1373\u1369",
        "422": "\u136c\u137b\u1373\u136a",
        "423": "\u136c\u137b\u1373\u136b",
        "424": "\u136c\u137b\u1373\u136c",
        "425": "\u136c\u137b\u1373\u136d",
        "426": "\u136c\u137b\u1373\u136e",
        "427": "\u136c\u137b\u1373\u136f",
        "428": "\u136c\u137b\u1373\u1370",
        "429": "\u136c\u137b\u1373\u1371",
        "430": "\u136c\u137b\u1374",
        "431": "\u136c\u137b\u1374\u1369",
        "432": "\u136c\u137b\u1374\u136a",
        "433": "\u136c\u137b\u1374\u136b",
        "434": "\u136c\u137b\u1374\u136c",
        "435": "\u136c\u137b\u1374\u136d",
        "436": "\u136c\u137b\u1374\u136e",
        "437": "\u136c\u137b\u1374\u136f",
        "438": "\u136c\u137b\u1374\u1370",
        "439": "\u136c\u137b\u1374\u1371",
        "440": "\u136c\u137b\u1375",
        "441": "\u136c\u137b\u1375\u1369",
        "442": "\u136c\u137b\u1375\u136a",
        "443": "\u136c\u137b\u1375\u136b",
        "444": "\u136c\u137b\u1375\u136c",
        "445": "\u136c\u137b\u1375\u136d",
        "446": "\u136c\u137b\u1375\u136e",
        "447": "\u136c\u137b\u1375\u136f",
        "448": "\u136c\u137b\u1375\u1370",
        "449": "\u136c\u137b\u1375\u1371",
        "450": "\u136c\u137b\u1376",
        "451": "\u136c\u137b\u1376\u1369",
        "452": "\u136c\u137b\u1376\u136a",
        "453": "\u136c\u137b\u1376\u136b",
        "454": "\u136c\u137b\u1376\u136c",
        "455": "\u136c\u137b\u1376\u136d",
        "456": "\u136c\u137b\u1376\u136e",
        "457": "\u136c\u137b\u1376\u136f",
        "458": "\u136c\u137b\u1376\u1370",
        "459": "\u136c\u137b\u1376\u1371",
        "460": "\u136c\u137b\u1377",
        "461": "\u136c\u137b\u1377\u1369",
        "462": "\u136c\u137b\u1377\u136a",
        "463": "\u136c\u137b\u1377\u136b",
        "464": "\u136c\u137b\u1377\u136c",
        "465": "\u136c\u137b\u1377\u136d",
        "466": "\u136c\u137b\u1377\u136e",
        "467": "\u136c\u137b\u1377\u136f",
        "468": "\u136c\u137b\u1377\u1370",
        "469": "\u136c\u137b\u1377\u1371",
        "470": "\u136c\u137b\u1378",
        "471": "\u136c\u137b\u1378\u1369",
        "472": "\u136c\u137b\u1378\u136a",
        "473": "\u136c\u137b\u1378\u136b",
        "474": "\u136c\u137b\u1378\u136c",
        "475": "\u136c\u137b\u1378\u136d",
        "476": "\u136c\u137b\u1378\u136e",
        "477": "\u136c\u137b\u1378\u136f",
        "478": "\u136c\u137b\u1378\u1370",
        "479": "\u136c\u137b\u1378\u1371",
        "480": "\u136c\u137b\u1379",
        "481": "\u136c\u137b\u1379\u1369",
        "482": "\u136c\u137b\u1379\u136a",
        "483": "\u136c\u137b\u1379\u136b",
        "484": "\u136c\u137b\u1379\u136c",
        "485": "\u136c\u137b\u1379\u136d",
        "486": "\u136c\u137b\u1379\u136e",
        "487": "\u136c\u137b\u1379\u136f",
        "488": "\u136c\u137b\u1379\u1370",
        "489": "\u136c\u137b\u1379\u1371",
        "490": "\u136c\u137b\u137a",
        "491": "\u136c\u137b\u137a\u1369",
        "492": "\u136c\u137b\u137a\u136a",
        "493": "\u136c\u137b\u137a\u136b",
        "494": "\u136c\u137b\u137a\u136c",
        "495": "\u136c\u137b\u137a\u136d",
        "496": "\u136c\u137b\u137a\u136e",
        "497": "\u136c\u137b\u137a\u136f",
        "498": "\u136c\u137b\u137a\u1370",
        "499": "\u136c\u137b\u137a\u1371",
        "500": "\u136d\u137b",
        "501": "\u136d\u137b\u1369",
        "502": "\u136d\u137b\u136a",
        "503": "\u136d\u137b\u136b",
        "504": "\u136d\u137b\u136c",
        "505": "\u136d\u137b\u136d",
        "506": "\u136d\u137b\u136e",
        "507": "\u136d\u137b\u136f",
        "508": "\u136d\u137b\u1370",
        "509": "\u136d\u137b\u1371",
        "510": "\u136d\u137b\u1372",
        "511": "\u136d\u137b\u1372\u1369",
        "512": "\u136d\u137b\u1372\u136a",
        "513": "\u136d\u137b\u1372\u136b",
        "514": "\u136d\u137b\u1372\u136c",
        "515": "\u136d\u137b\u1372\u136d",
        "516": "\u136d\u137b\u1372\u136e",
        "517": "\u136d\u137b\u1372\u136f",
        "518": "\u136d\u137b\u1372\u1370",
        "519": "\u136d\u137b\u1372\u1371",
        "520": "\u136d\u137b\u1373",
        "521": "\u136d\u137b\u1373\u1369",
        "522": "\u136d\u137b\u1373\u136a",
        "523": "\u136d\u137b\u1373\u136b",
        "524": "\u136d\u137b\u1373\u136c",
        "525": "\u136d\u137b\u1373\u136d",
        "526": "\u136d\u137b\u1373\u136e",
        "527": "\u136d\u137b\u1373\u136f",
        "528": "\u136d\u137b\u1373\u1370",
        "529": "\u136d\u137b\u1373\u1371",
        "530": "\u136d\u137b\u1374",
        "531": "\u136d\u137b\u1374\u1369",
        "532": "\u136d\u137b\u1374\u136a",
        "533": "\u136d\u137b\u1374\u136b",
        "534": "\u136d\u137b\u1374\u136c",
        "535": "\u136d\u137b\u1374\u136d",
        "536": "\u136d\u137b\u1374\u136e",
        "537": "\u136d\u137b\u1374\u136f",
        "538": "\u136d\u137b\u1374\u1370",
        "539": "\u136d\u137b\u1374\u1371",
        "540": "\u136d\u137b\u1375",
        "541": "\u136d\u137b\u1375\u1369",
        "542": "\u136d\u137b\u1375\u136a",
        "543": "\u136d\u137b\u1375\u136b",
        "544": "\u136d\u137b\u1375\u136c",
        "545": "\u136d\u137b\u1375\u136d",
        "546": "\u136d\u137b\u1375\u136e",
        "547": "\u136d\u137b\u1375\u136f",
        "548": "\u136d\u137b\u1375\u1370",
        "549": "\u136d\u137b\u1375\u1371",
        "550": "\u136d\u137b\u1376",
        "551": "\u136d\u137b\u1376\u1369",
        "552": "\u136d\u137b\u1376\u136a",
        "553": "\u136d\u137b\u1376\u136b",
        "554": "\u136d\u137b\u1376\u136c",
        "555": "\u136d\u137b\u1376\u136d",
        "556": "\u136d\u137b\u1376\u136e",
        "557": "\u136d\u137b\u1376\u136f",
        "558": "\u136d\u137b\u1376\u1370",
        "559": "\u136d\u137b\u1376\u1371",
        "560": "\u136d\u137b\u1377",
        "561": "\u136d\u137b\u1377\u1369",
        "562": "\u136d\u137b\u1377\u136a",
        "563": "\u136d\u137b\u1377\u136b",
        "564": "\u136d\u137b\u1377\u136c",
        "565": "\u136d\u137b\u1377\u136d",
        "566": "\u136d\u137b\u1377\u136e",
        "567": "\u136d\u137b\u1377\u136f",
        "568": "\u136d\u137b\u1377\u1370",
        "569": "\u136d\u137b\u1377\u1371",
        "570": "\u136d\u137b\u1378",
        "571": "\u136d\u137b\u1378\u1369",
        "572": "\u136d\u137b\u1378\u136a",
        "573": "\u136d\u137b\u1378\u136b",
        "574": "\u136d\u137b\u1378\u136c",
        "575": "\u136d\u137b\u1378\u136d",
        "576": "\u136d\u137b\u1378\u136e",
        "577": "\u136d\u137b\u1378\u136f",
        "578": "\u136d\u137b\u1378\u1370",
        "579": "\u136d\u137b\u1378\u1371",
        "580": "\u136d\u137b\u1379",
        "581": "\u136d\u137b\u1379\u1369",
        "582": "\u136d\u137b\u1379\u136a",
        "583": "\u136d\u137b\u1379\u136b",
        "584": "\u136d\u137b\u1379\u136c",
        "585": "\u136d\u137b\u1379\u136d",
        "586": "\u136d\u137b\u1379\u136e",
        "587": "\u136d\u137b\u1379\u136f",
        "588": "\u136d\u137b\u1379\u1370",
        "589": "\u136d\u137b\u1379\u1371",
        "590": "\u136d\u137b\u137a",
        "591": "\u136d\u137b\u137a\u1369",
        "592": "\u136d\u137b\u137a\u136a",
        "593": "\u136d\u137b\u137a\u136b",
        "594": "\u136d\u137b\u137a\u136c",
        "595": "\u136d\u137b\u137a\u136d",
        "596": "\u136d\u137b\u137a\u136e",
        "597": "\u136d\u137b\u137a\u136f",
        "598": "\u136d\u137b\u137a\u1370",
        "599": "\u136d\u137b\u137a\u1371",
        "600": "\u136e\u137b",
        "601": "\u136e\u137b\u1369",
        "602": "\u136e\u137b\u136a",
        "603": "\u136e\u137b\u136b",
        "604": "\u136e\u137b\u136c",
        "605": "\u136e\u137b\u136d",
        "606": "\u136e\u137b\u136e",
        "607": "\u136e\u137b\u136f",
        "608": "\u136e\u137b\u1370",
        "609": "\u136e\u137b\u1371",
        "610": "\u136e\u137b\u1372",
        "611": "\u136e\u137b\u1372\u1369",
        "612": "\u136e\u137b\u1372\u136a",
        "613": "\u136e\u137b\u1372\u136b",
        "614": "\u136e\u137b\u1372\u136c",
        "615": "\u136e\u137b\u1372\u136d",
        "616": "\u136e\u137b\u1372\u136e",
        "617": "\u136e\u137b\u1372\u136f",
        "618": "\u136e\u137b\u1372\u1370",
        "619": "\u136e\u137b\u1372\u1371",
        "620": "\u136e\u137b\u1373",
        "621": "\u136e\u137b\u1373\u1369",
        "622": "\u136e\u137b\u1373\u136a",
        "623": "\u136e\u137b\u1373\u136b",
        "624": "\u136e\u137b\u1373\u136c",
        "625": "\u136e\u137b\u1373\u136d",
        "626": "\u136e\u137b\u1373\u136e",
        "627": "\u136e\u137b\u1373\u136f",
        "628": "\u136e\u137b\u1373\u1370",
        "629": "\u136e\u137b\u1373\u1371",
        "630": "\u136e\u137b\u1374",
        "631": "\u136e\u137b\u1374\u1369",
        "632": "\u136e\u137b\u1374\u136a",
        "633": "\u136e\u137b\u1374\u136b",
        "634": "\u136e\u137b\u1374\u136c",
        "635": "\u136e\u137b\u1374\u136d",
        "636": "\u136e\u137b\u1374\u136e",
        "637": "\u136e\u137b\u1374\u136f",
        "638": "\u136e\u137b\u1374\u1370",
        "639": "\u136e\u137b\u1374\u1371",
        "640": "\u136e\u137b\u1375",
        "641": "\u136e\u137b\u1375\u1369",
        "642": "\u136e\u137b\u1375\u136a",
        "643": "\u136e\u137b\u1375\u136b",
        "644": "\u136e\u137b\u1375\u136c",
        "645": "\u136e\u137b\u1375\u136d",
        "646": "\u136e\u137b\u1375\u136e",
        "647": "\u136e\u137b\u1375\u136f",
        "648": "\u136e\u137b\u1375\u1370",
        "649": "\u136e\u137b\u1375\u1371",
        "650": "\u136e\u137b\u1376",
        "651": "\u136e\u137b\u1376\u1369",
        "652": "\u136e\u137b\u1376\u136a",
        "653": "\u136e\u137b\u1376\u136b",
        "654": "\u136e\u137b\u1376\u136c",
        "655": "\u136e\u137b\u1376\u136d",
        "656": "\u136e\u137b\u1376\u136e",
        "657": "\u136e\u137b\u1376\u136f",
        "658": "\u136e\u137b\u1376\u1370",
        "659": "\u136e\u137b\u1376\u1371",
        "660": "\u136e\u137b\u1377",
        "661": "\u136e\u137b\u1377\u1369",
        "662": "\u136e\u137b\u1377\u136a",
        "663": "\u136e\u137b\u1377\u136b",
        "664": "\u136e\u137b\u1377\u136c",
        "665": "\u136e\u137b\u1377\u136d",
        "666": "\u136e\u137b\u1377\u136e",
        "667": "\u136e\u137b\u1377\u136f",
        "668": "\u136e\u137b\u1377\u1370",
        "669": "\u136e\u137b\u1377\u1371",
        "670": "\u136e\u137b\u1378",
        "671": "\u136e\u137b\u1378\u1369",
        "672": "\u136e\u137b\u1378\u136a",
        "673": "\u136e\u137b\u1378\u136b",
        "674": "\u136e\u137b\u1378\u136c",
        "675": "\u136e\u137b\u1378\u136d",
        "676": "\u136e\u137b\u1378\u136e",
        "677": "\u136e\u137b\u1378\u136f",
        "678": "\u136e\u137b\u1378\u1370",
        "679": "\u136e\u137b\u1378\u1371",
        "680": "\u136e\u137b\u1379",
        "681": "\u136e\u137b\u1379\u1369",
        "682": "\u136e\u137b\u1379\u136a",
        "683": "\u136e\u137b\u1379\u136b",
        "684": "\u136e\u137b\u1379\u136c",
        "685": "\u136e\u137b\u1379\u136d",
        "686": "\u136e\u137b\u1379\u136e",
        "687": "\u136e\u137b\u1379\u136f",
        "688": "\u136e\u137b\u1379\u1370",
        "689": "\u136e\u137b\u1379\u1371",
        "690": "\u136e\u137b\u137a",
        "691": "\u136e\u137b\u137a\u1369",
        "692": "\u136e\u137b\u137a\u136a",
        "693": "\u136e\u137b\u137a\u136b",
        "694": "\u136e\u137b\u137a\u136c",
        "695": "\u136e\u137b\u137a\u136d",
        "696": "\u136e\u137b\u137a\u136e",
        "697": "\u136e\u137b\u137a\u136f",
        "698": "\u136e\u137b\u137a\u1370",
        "699": "\u136e\u137b\u137a\u1371",
        "700": "\u136f\u137b",
        "701": "\u136f\u137b\u1369",
        "702": "\u136f\u137b\u136a",
        "703": "\u136f\u137b\u136b",
        "704": "\u136f\u137b\u136c",
        "705": "\u136f\u137b\u136d",
        "706": "\u136f\u137b\u136e",
        "707": "\u136f\u137b\u136f",
        "708": "\u136f\u137b\u1370",
        "709": "\u136f\u137b\u1371",
        "710": "\u136f\u137b\u1372",
        "711": "\u136f\u137b\u1372\u1369",
        "712": "\u136f\u137b\u1372\u136a",
        "713": "\u136f\u137b\u1372\u136b",
        "714": "\u136f\u137b\u1372\u136c",
        "715": "\u136f\u137b\u1372\u136d",
        "716": "\u136f\u137b\u1372\u136e",
        "717": "\u136f\u137b\u1372\u136f",
        "718": "\u136f\u137b\u1372\u1370",
        "719": "\u136f\u137b\u1372\u1371",
        "720": "\u136f\u137b\u1373",
        "721": "\u136f\u137b\u1373\u1369",
        "722": "\u136f\u137b\u1373\u136a",
        "723": "\u136f\u137b\u1373\u136b",
        "724": "\u136f\u137b\u1373\u136c",
        "725": "\u136f\u137b\u1373\u136d",
        "726": "\u136f\u137b\u1373\u136e",
        "727": "\u136f\u137b\u1373\u136f",
        "728": "\u136f\u137b\u1373\u1370",
        "729": "\u136f\u137b\u1373\u1371",
        "730": "\u136f\u137b\u1374",
        "731": "\u136f\u137b\u1374\u1369",
        "732": "\u136f\u137b\u1374\u136a",
        "733": "\u136f\u137b\u1374\u136b",
        "734": "\u136f\u137b\u1374\u136c",
        "735": "\u136f\u137b\u1374\u136d",
        "736": "\u136f\u137b\u1374\u136e",
        "737": "\u136f\u137b\u1374\u136f",
        "738": "\u136f\u137b\u1374\u1370",
        "739": "\u136f\u137b\u1374\u1371",
        "740": "\u136f\u137b\u1375",
        "741": "\u136f\u137b\u1375\u1369",
        "742": "\u136f\u137b\u1375\u136a",
        "743": "\u136f\u137b\u1375\u136b",
        "744": "\u136f\u137b\u1375\u136c",
        "745": "\u136f\u137b\u1375\u136d",
        "746": "\u136f\u137b\u1375\u136e",
        "747": "\u136f\u137b\u1375\u136f",
        "748": "\u136f\u137b\u1375\u1370",
        "749": "\u136f\u137b\u1375\u1371",
        "750": "\u136f\u137b\u1376",
        "751": "\u136f\u137b\u1376\u1369",
        "752": "\u136f\u137b\u1376\u136a",
        "753": "\u136f\u137b\u1376\u136b",
        "754": "\u136f\u137b\u1376\u136c",
        "755": "\u136f\u137b\u1376\u136d",
        "756": "\u136f\u137b\u1376\u136e",
        "757": "\u136f\u137b\u1376\u136f",
        "758": "\u136f\u137b\u1376\u1370",
        "759": "\u136f\u137b\u1376\u1371",
        "760": "\u136f\u137b\u1377",
        "761": "\u136f\u137b\u1377\u1369",
        "762": "\u136f\u137b\u1377\u136a",
        "763": "\u136f\u137b\u1377\u136b",
        "764": "\u136f\u137b\u1377\u136c",
        "765": "\u136f\u137b\u1377\u136d",
        "766": "\u136f\u137b\u1377\u136e",
        "767": "\u136f\u137b\u1377\u136f",
        "768": "\u136f\u137b\u1377\u1370",
        "769": "\u136f\u137b\u1377\u1371",
        "770": "\u136f\u137b\u1378",
        "771": "\u136f\u137b\u1378\u1369",
        "772": "\u136f\u137b\u1378\u136a",
        "773": "\u136f\u137b\u1378\u136b",
        "774": "\u136f\u137b\u1378\u136c",
        "775": "\u136f\u137b\u1378\u136d",
        "776": "\u136f\u137b\u1378\u136e",
        "777": "\u136f\u137b\u1378\u136f",
        "778": "\u136f\u137b\u1378\u1370",
        "779": "\u136f\u137b\u1378\u1371",
        "780": "\u136f\u137b\u1379",
        "781": "\u136f\u137b\u1379\u1369",
        "782": "\u136f\u137b\u1379\u136a",
        "783": "\u136f\u137b\u1379\u136b",
        "784": "\u136f\u137b\u1379\u136c",
        "785": "\u136f\u137b\u1379\u136d",
        "786": "\u136f\u137b\u1379\u136e",
        "787": "\u136f\u137b\u1379\u136f",
        "788": "\u136f\u137b\u1379\u1370",
        "789": "\u136f\u137b\u1379\u1371",
        "790": "\u136f\u137b\u137a",
        "791": "\u136f\u137b\u137a\u1369",
        "792": "\u136f\u137b\u137a\u136a",
        "793": "\u136f\u137b\u137a\u136b",
        "794": "\u136f\u137b\u137a\u136c",
        "795": "\u136f\u137b\u137a\u136d",
        "796": "\u136f\u137b\u137a\u136e",
        "797": "\u136f\u137b\u137a\u136f",
        "798": "\u136f\u137b\u137a\u1370",
        "799": "\u136f\u137b\u137a\u1371",
        "800": "\u1370\u137b",
        "801": "\u1370\u137b\u1369",
        "802": "\u1370\u137b\u136a",
        "803": "\u1370\u137b\u136b",
        "804": "\u1370\u137b\u136c",
        "805": "\u1370\u137b\u136d",
        "806": "\u1370\u137b\u136e",
        "807": "\u1370\u137b\u136f",
        "808": "\u1370\u137b\u1370",
        "809": "\u1370\u137b\u1371",
        "810": "\u1370\u137b\u1372",
        "811": "\u1370\u137b\u1372\u1369",
        "812": "\u1370\u137b\u1372\u136a",
        "813": "\u1370\u137b\u1372\u136b",
        "814": "\u1370\u137b\u1372\u136c",
        "815": "\u1370\u137b\u1372\u136d",
        "816": "\u1370\u137b\u1372\u136e",
        "817": "\u1370\u137b\u1372\u136f",
        "818": "\u1370\u137b\u1372\u1370",
        "819": "\u1370\u137b\u1372\u1371",
        "820": "\u1370\u137b\u1373",
        "821": "\u1370\u137b\u1373\u1369",
        "822": "\u1370\u137b\u1373\u136a",
        "823": "\u1370\u137b\u1373\u136b",
        "824": "\u1370\u137b\u1373\u136c",
        "825": "\u1370\u137b\u1373\u136d",
        "826": "\u1370\u137b\u1373\u136e",
        "827": "\u1370\u137b\u1373\u136f",
        "828": "\u1370\u137b\u1373\u1370",
        "829": "\u1370\u137b\u1373\u1371",
        "830": "\u1370\u137b\u1374",
        "831": "\u1370\u137b\u1374\u1369",
        "832": "\u1370\u137b\u1374\u136a",
        "833": "\u1370\u137b\u1374\u136b",
        "834": "\u1370\u137b\u1374\u136c",
        "835": "\u1370\u137b\u1374\u136d",
        "836": "\u1370\u137b\u1374\u136e",
        "837": "\u1370\u137b\u1374\u136f",
        "838": "\u1370\u137b\u1374\u1370",
        "839": "\u1370\u137b\u1374\u1371",
        "840": "\u1370\u137b\u1375",
        "841": "\u1370\u137b\u1375\u1369",
        "842": "\u1370\u137b\u1375\u136a",
        "843": "\u1370\u137b\u1375\u136b",
        "844": "\u1370\u137b\u1375\u136c",
        "845": "\u1370\u137b\u1375\u136d",
        "846": "\u1370\u137b\u1375\u136e",
        "847": "\u1370\u137b\u1375\u136f",
        "848": "\u1370\u137b\u1375\u1370",
        "849": "\u1370\u137b\u1375\u1371",
        "850": "\u1370\u137b\u1376",
        "851": "\u1370\u137b\u1376\u1369",
        "852": "\u1370\u137b\u1376\u136a",
        "853": "\u1370\u137b\u1376\u136b",
        "854": "\u1370\u137b\u1376\u136c",
        "855": "\u1370\u137b\u1376\u136d",
        "856": "\u1370\u137b\u1376\u136e",
        "857": "\u1370\u137b\u1376\u136f",
        "858": "\u1370\u137b\u1376\u1370",
        "859": "\u1370\u137b\u1376\u1371",
        "860": "\u1370\u137b\u1377",
        "861": "\u1370\u137b\u1377\u1369",
        "862": "\u1370\u137b\u1377\u136a",
        "863": "\u1370\u137b\u1377\u136b",
        "864": "\u1370\u137b\u1377\u136c",
        "865": "\u1370\u137b\u1377\u136d",
        "866": "\u1370\u137b\u1377\u136e",
        "867": "\u1370\u137b\u1377\u136f",
        "868": "\u1370\u137b\u1377\u1370",
        "869": "\u1370\u137b\u1377\u1371",
        "870": "\u1370\u137b\u1378",
        "871": "\u1370\u137b\u1378\u1369",
        "872": "\u1370\u137b\u1378\u136a",
        "873": "\u1370\u137b\u1378\u136b",
        "874": "\u1370\u137b\u1378\u136c",
        "875": "\u1370\u137b\u1378\u136d",
        "876": "\u1370\u137b\u1378\u136e",
        "877": "\u1370\u137b\u1378\u136f",
        "878": "\u1370\u137b\u1378\u1370",
        "879": "\u1370\u137b\u1378\u1371",
        "880": "\u1370\u137b\u1379",
        "881": "\u1370\u137b\u1379\u1369",
        "882": "\u1370\u137b\u1379\u136a",
        "883": "\u1370\u137b\u1379\u136b",
        "884": "\u1370\u137b\u1379\u136c",
        "885": "\u1370\u137b\u1379\u136d",
        "886": "\u1370\u137b\u1379\u136e",
        "887": "\u1370\u137b\u1379\u136f",
        "888": "\u1370\u137b\u1379\u1370",
        "889": "\u1370\u137b\u1379\u1371",
        "890": "\u1370\u137b\u137a",
        "891": "\u1370\u137b\u137a\u1369",
        "892": "\u1370\u137b\u137a\u136a",
        "893": "\u1370\u137b\u137a\u136b",
        "894": "\u1370\u137b\u137a\u136c",
        "895": "\u1370\u137b\u137a\u136d",
        "896": "\u1370\u137b\u137a\u136e",
        "897": "\u1370\u137b\u137a\u136f",
        "898": "\u1370\u137b\u137a\u1370",
        "899": "\u1370\u137b\u137a\u1371",
        "900": "\u1371\u137b",
        "901": "\u1371\u137b\u1369",
        "902": "\u1371\u137b\u136a",
        "903": "\u1371\u137b\u136b",
        "904": "\u1371\u137b\u136c",
        "905": "\u1371\u137b\u136d",
        "906": "\u1371\u137b\u136e",
        "907": "\u1371\u137b\u136f",
        "908": "\u1371\u137b\u1370",
        "909": "\u1371\u137b\u1371",
        "910": "\u1371\u137b\u1372",
        "911": "\u1371\u137b\u1372\u1369",
        "912": "\u1371\u137b\u1372\u136a",
        "913": "\u1371\u137b\u1372\u136b",
        "914": "\u1371\u137b\u1372\u136c",
        "915": "\u1371\u137b\u1372\u136d",
        "916": "\u1371\u137b\u1372\u136e",
        "917": "\u1371\u137b\u1372\u136f",
        "918": "\u1371\u137b\u1372\u1370",
        "919": "\u1371\u137b\u1372\u1371",
        "920": "\u1371\u137b\u1373",
        "921": "\u1371\u137b\u1373\u1369",
        "922": "\u1371\u137b\u1373\u136a",
        "923": "\u1371\u137b\u1373\u136b",
        "924": "\u1371\u137b\u1373\u136c",
        "925": "\u1371\u137b\u1373\u136d",
        "926": "\u1371\u137b\u1373\u136e",
        "927": "\u1371\u137b\u1373\u136f",
        "928": "\u1371\u137b\u1373\u1370",
        "929": "\u1371\u137b\u1373\u1371",
        "930": "\u1371\u137b\u1374",
        "931": "\u1371\u137b\u1374\u1369",
        "932": "\u1371\u137b\u1374\u136a",
        "933": "\u1371\u137b\u1374\u136b",
        "934": "\u1371\u137b\u1374\u136c",
        "935": "\u1371\u137b\u1374\u136d",
        "936": "\u1371\u137b\u1374\u136e",
        "937": "\u1371\u137b\u1374\u136f",
        "938": "\u1371\u137b\u1374\u1370",
        "939": "\u1371\u137b\u1374\u1371",
        "940": "\u1371\u137b\u1375",
        "941": "\u1371\u137b\u1375\u1369",
        "942": "\u1371\u137b\u1375\u136a",
        "943": "\u1371\u137b\u1375\u136b",
        "944": "\u1371\u137b\u1375\u136c",
        "945": "\u1371\u137b\u1375\u136d",
        "946": "\u1371\u137b\u1375\u136e",
        "947": "\u1371\u137b\u1375\u136f",
        "948": "\u1371\u137b\u1375\u1370",
        "949": "\u1371\u137b\u1375\u1371",
        "950": "\u1371\u137b\u1376",
        "951": "\u1371\u137b\u1376\u1369",
        "952": "\u1371\u137b\u1376\u136a",
        "953": "\u1371\u137b\u1376\u136b",
        "954": "\u1371\u137b\u1376\u136c",
        "955": "\u1371\u137b\u1376\u136d",
        "956": "\u1371\u137b\u1376\u136e",
        "957": "\u1371\u137b\u1376\u136f",
        "958": "\u1371\u137b\u1376\u1370",
        "959": "\u1371\u137b\u1376\u1371",
        "960": "\u1371\u137b\u1377",
        "961": "\u1371\u137b\u1377\u1369",
        "962": "\u1371\u137b\u1377\u136a",
        "963": "\u1371\u137b\u1377\u136b",
        "964": "\u1371\u137b\u1377\u136c",
        "965": "\u1371\u137b\u1377\u136d",
        "966": "\u1371\u137b\u1377\u136e",
        "967": "\u1371\u137b\u1377\u136f",
        "968": "\u1371\u137b\u1377\u1370",
        "969": "\u1371\u137b\u1377\u1371",
        "970": "\u1371\u137b\u1378",
        "971": "\u1371\u137b\u1378\u1369",
        "972": "\u1371\u137b\u1378\u136a",
        "973": "\u1371\u137b\u1378\u136b",
        "974": "\u1371\u137b\u1378\u136c",
        "975": "\u1371\u137b\u1378\u136d",
        "976": "\u1371\u137b\u1378\u136e",
        "977": "\u1371\u137b\u1378\u136f",
        "978": "\u1371\u137b\u1378\u1370",
        "979": "\u1371\u137b\u1378\u1371",
        "980": "\u1371\u137b\u1379",
        "981": "\u1371\u137b\u1379\u1369",
        "982": "\u1371\u137b\u1379\u136a",
        "983": "\u1371\u137b\u1379\u136b",
        "984": "\u1371\u137b\u1379\u136c",
        "985": "\u1371\u137b\u1379\u136d",
        "986": "\u1371\u137b\u1379\u136e",
        "987": "\u1371\u137b\u1379\u136f",
        "988": "\u1371\u137b\u1379\u1370",
        "989": "\u1371\u137b\u1379\u1371",
        "990": "\u1371\u137b\u137a",
        "991": "\u1371\u137b\u137a\u1369",
        "992": "\u1371\u137b\u137a\u136a",
        "993": "\u1371\u137b\u137a\u136b",
        "994": "\u1371\u137b\u137a\u136c",
        "995": "\u1371\u137b\u137a\u136d",
        "996": "\u1371\u137b\u137a\u136e",
        "997": "\u1371\u137b\u137a\u136f",
        "998": "\u1371\u137b\u137a\u1370",
        "999": "\u1371\u137b\u137a\u1371",
        "1000": "\u1372\u137b"
    }
}
